ab_client/token_issuer/__init__.py
ab_client/token_issuer/clients/__init__.py
ab_client/token_issuer/clients/async_client.py
ab_client/token_issuer/clients/sync_client.py
ab_client/token_issuer/exceptions/__init__.py
ab_client/token_issuer/exceptions/http_exception.py
ab_client/token_issuer/models/AuthenticateRequest.py
ab_client/token_issuer/models/BrowserlessService.py
ab_client/token_issuer/models/CDPGUIService.py
ab_client/token_issuer/models/HTTPValidationError.py
ab_client/token_issuer/models/ImpersonationOAuth2Flow.py
ab_client/token_issuer/models/Impersonator.py
ab_client/token_issuer/models/ImpersonatorTool.py
ab_client/token_issuer/models/OAuth2TokenIssuer.py
ab_client/token_issuer/models/OIDCConfig.py
ab_client/token_issuer/models/Oauth2Client.py
ab_client/token_issuer/models/Oauth2ClientType.py
ab_client/token_issuer/models/Oauth2Flow.py
ab_client/token_issuer/models/Oauth2FlowType.py
ab_client/token_issuer/models/PKCEOAuth2Client.py
ab_client/token_issuer/models/PKCEOAuth2TokenIssuer.py
ab_client/token_issuer/models/PlaywrightCDPBrowserlessImpersonator.py
ab_client/token_issuer/models/PlaywrightCDPImpersonator.py
ab_client/token_issuer/models/PlaywrightImpersonator.py
ab_client/token_issuer/models/RefreshRequest.py
ab_client/token_issuer/models/RefreshTokenRequest.py
ab_client/token_issuer/models/StandardOAuth2Client.py
ab_client/token_issuer/models/TemplateImpersonator.py
ab_client/token_issuer/models/TemplateOAuth2Flow.py
ab_client/token_issuer/models/TemplateTokenIssuer.py
ab_client/token_issuer/models/TokenIssuer.py
ab_client/token_issuer/models/TokenIssuerType.py
ab_client/token_issuer/models/ValidationError.py
ab_client/token_issuer/models/__init__.py
ab_client_token_issuer-1.1.1.dist-info/METADATA
ab_client_token_issuer-1.1.1.dist-info/WHEEL
ab_client_token_issuer-1.1.1.dist-info/licenses/LICENSE
ab_client_token_issuer-1.1.1.dist-info/RECORD
